{
  "status": 0,
  "result": [
    {
      "createdById": "0051U000001ugPoQAI",
      "createdByName": "salesforce.com, inc.",
      "createdDate": "2018-12-19T20:50:35.000Z",
      "fileName": "layouts/ListEmail-List Email Layout.layout",
      "fullName": "ListEmail-List Email Layout",
      "id": "00h1U000000Urm7QAC",
      "lastModifiedById": "0051U000001ugPoQAI",
      "lastModifiedByName": "salesforce.com, inc.",
      "lastModifiedDate": "2018-12-19T20:50:35.000Z",
      "manageableState": "unmanaged",
      "type": "Layout"
    },
    {
      "createdById": "0051U000005XFFIQA4",
      "createdByName": "AstoundOldUser",
      "createdDate": "2019-06-20T14:47:49.000Z",
      "fileName": "layouts/et4ae5__SendDefinition__c-Trackable Send Definition Layout.layout",
      "fullName": "et4ae5__SendDefinition__c-Trackable Send Definition Layout",
      "id": "00h1U000007TT2iQAG",
      "lastModifiedById": "0051U000005XFFIQA4",
      "lastModifiedByName": "AstoundOldUser",
      "lastModifiedDate": "2019-06-20T14:47:49.000Z",
      "manageableState": "installed",
      "namespacePrefix": "et4ae5",
      "type": "Layout"
    },
    {
      "createdById": "0051U000001ugPoQAI",
      "createdByName": "salesforce.com, inc.",
      "createdDate": "2022-03-02T18:56:43.000Z",
      "fileName": "layouts/SurveyInvitation-Survey Invitation Layout.layout",
      "fullName": "SurveyInvitation-Survey Invitation Layout",
      "id": "00h1U000007uTwBQAU",
      "lastModifiedById": "0051U000001ugPoQAI",
      "lastModifiedByName": "salesforce.com, inc.",
      "lastModifiedDate": "2022-03-02T18:56:43.000Z",
      "manageableState": "unmanaged",
      "type": "Layout"
    },
    {
      "createdById": "0051U000005XFFIQA4",
      "createdByName": "AstoundOldUser",
      "createdDate": "2019-08-07T14:28:10.000Z",
      "fileName": "layouts/Card_Replacement_Request__c-Card Replacement Request Layout.layout",
      "fullName": "Card_Replacement_Request__c-Card Replacement Request Layout",
      "id": "00h1U000007FkTrQAK",
      "lastModifiedById": "0051U000005XFFIQA4",
      "lastModifiedByName": "AstoundOldUser",
      "lastModifiedDate": "2019-08-21T15:51:15.000Z",
      "manageableState": "unmanaged",
      "type": "Layout"
    },
    {
      "createdById": "0051U000001L3PBQA0",
      "createdByName": "Craig Turner",
      "createdDate": "2018-12-19T20:27:32.000Z",
      "fileName": "layouts/Solution-Solution Layout.layout",
      "fullName": "Solution-Solution Layout",
      "id": "00h1U000002TMX6QAO",
      "lastModifiedById": "0051U000001L3PBQA0",
      "lastModifiedByName": "Craig Turner",
      "lastModifiedDate": "2018-12-19T20:27:32.000Z",
      "manageableState": "unmanaged",
      "type": "Layout"
    },
    {
      "createdById": "0051U000005XFFIQA4",
      "createdByName": "AstoundOldUser",
      "createdDate": "2019-06-20T14:47:21.000Z",
      "fileName": "layouts/et4ae5__SendJunction__c-Send Junction Layout.layout",
      "fullName": "et4ae5__SendJunction__c-Send Junction Layout",
      "id": "00h1U000007TT2aQAG",
      "lastModifiedById": "0051U000005XFFIQA4",
      "lastModifiedByName": "AstoundOldUser",
      "lastModifiedDate": "2019-06-20T14:47:49.000Z",
      "manageableState": "installed",
      "namespacePrefix": "et4ae5",
      "type": "Layout"
    },
    {
      "createdById": "0051U000005XFFIQA4",
      "createdByName": "AstoundOldUser",
      "createdDate": "2019-08-02T07:53:20.000Z",
      "fileName": "layouts/Case-Contact Us.layout",
      "fullName": "Case-Contact Us",
      "id": "00h1U000007FjhhQAC",
      "lastModifiedById": "0051U0000060JrUQAU",
      "lastModifiedByName": "Christine Lamonde",
      "lastModifiedDate": "2022-06-06T20:53:12.000Z",
      "manageableState": "unmanaged",
      "type": "Layout"
    },
    {
      "createdById": "0051U000005XFFIQA4",
      "createdByName": "AstoundOldUser",
      "createdDate": "2020-07-31T19:39:17.000Z",
      "fileName": "layouts/LiveChatTranscriptEvent-Chat Transcript Event Layout.layout",
      "fullName": "LiveChatTranscriptEvent-Chat Transcript Event Layout",
      "id": "00h1U000007pUGGQA2",
      "lastModifiedById": "0051U000005XFFIQA4",
      "lastModifiedByName": "AstoundOldUser",
      "lastModifiedDate": "2020-07-31T19:39:17.000Z",
      "manageableState": "unmanaged",
      "type": "Layout"
    },
    {
      "createdById": "0051U000005XLwAQAW",
      "createdByName": "Marketing Cloud",
      "createdDate": "2021-02-13T14:06:19.000Z",
      "fileName": "layouts/et4ae5__MC_CDC_Journey__c-MC CDC Journey Layout.layout",
      "fullName": "et4ae5__MC_CDC_Journey__c-MC CDC Journey Layout",
      "id": "00h1U000007q7eyQAA",
      "lastModifiedById": "0051U000005XLwAQAW",
      "lastModifiedByName": "Marketing Cloud",
      "lastModifiedDate": "2021-02-13T14:06:30.000Z",
      "manageableState": "installed",
      "namespacePrefix": "et4ae5",
      "type": "Layout"
    },
    {
      "createdById": "0051U000005tLLaQAM",
      "createdByName": "Toysrus AdminOldUser",
      "createdDate": "2020-09-16T05:21:25.000Z",
      "fileName": "layouts/Appeasement_Code__c-Appeasement Code Layout.layout",
      "fullName": "Appeasement_Code__c-Appeasement Code Layout",
      "id": "00h1U000007tQUlQAM",
      "lastModifiedById": "0051U000005tLLaQAM",
      "lastModifiedByName": "Toysrus AdminOldUser",
      "lastModifiedDate": "2020-09-16T05:21:39.000Z",
      "manageableState": "unmanaged",
      "type": "Layout"
    },
    {
      "createdById": "0051U000001L3PBQA0",
      "createdByName": "Craig Turner",
      "createdDate": "2018-12-19T20:27:32.000Z",
      "fileName": "layouts/CampaignMember-Campaign Member Page Layout.layout",
      "fullName": "CampaignMember-Campaign Member Page Layout",
      "id": "00h1U000002TMWtQAO",
      "lastModifiedById": "0051U000001L3PBQA0",
      "lastModifiedByName": "Craig Turner",
      "lastModifiedDate": "2018-12-19T20:27:32.000Z",
      "manageableState": "unmanaged",
      "type": "Layout"
    },
    {
      "createdById": "0051U000005tLLaQAM",
      "createdByName": "Toysrus AdminOldUser",
      "createdDate": "2020-10-19T13:25:33.000Z",
      "fileName": "layouts/lightningbuddy__Actions__c-Welcome Mat Actions Layout.layout",
      "fullName": "lightningbuddy__Actions__c-Welcome Mat Actions Layout",
      "id": "00h1U000007QfZkQAK",
      "lastModifiedById": "0051U000005tLLaQAM",
      "lastModifiedByName": "Toysrus AdminOldUser",
      "lastModifiedDate": "2020-10-22T19:06:58.000Z",
      "manageableState": "installed",
      "namespacePrefix": "lightningbuddy",
      "type": "Layout"
    },
    {
      "createdById": "0051U000005XFFIQA4",
      "createdByName": "AstoundOldUser",
      "createdDate": "2019-08-01T08:59:21.000Z",
      "fileName": "layouts/Payment_Information__c-Payment Information Layout.layout",
      "fullName": "Payment_Information__c-Payment Information Layout",
      "id": "00h1U000007FjZQQA0",
      "lastModifiedById": "0051U000005XFFIQA4",
      "lastModifiedByName": "AstoundOldUser",
      "lastModifiedDate": "2019-08-21T15:51:15.000Z",
      "manageableState": "unmanaged",
      "type": "Layout"
    },
    {
      "createdById": "0051U000001ugPoQAI",
      "createdByName": "salesforce.com, inc.",
      "createdDate": "2020-10-05T15:55:39.000Z",
      "fileName": "layouts/ServiceResource-Service Resource Layout.layout",
      "fullName": "ServiceResource-Service Resource Layout",
      "id": "00h1U000007tTKBQA2",
      "lastModifiedById": "0051U000005tLLaQAM",
      "lastModifiedByName": "Toysrus AdminOldUser",
      "lastModifiedDate": "2020-10-05T18:31:06.000Z",
      "manageableState": "unmanaged",
      "type": "Layout"
    },
    {
      "createdById": "0051U000001L3PBQA0",
      "createdByName": "Craig Turner",
      "createdDate": "2018-12-19T20:27:32.000Z",
      "fileName": "layouts/Opportunity-Opportunity Layout.layout",
      "fullName": "Opportunity-Opportunity Layout",
      "id": "00h1U000002TMWlQAO",
      "lastModifiedById": "0051U000001L3PBQA0",
      "lastModifiedByName": "Craig Turner",
      "lastModifiedDate": "2018-12-19T20:27:32.000Z",
      "manageableState": "unmanaged",
      "type": "Layout"
    },
    {
      "createdById": "0051U000001L3PBQA0",
      "createdByName": "Craig Turner",
      "createdDate": "2018-12-19T20:27:32.000Z",
      "fileName": "layouts/User-User Layout.layout",
      "fullName": "User-User Layout",
      "id": "00h1U000002TMX7QAO",
      "lastModifiedById": "0051U000005XFFIQA4",
      "lastModifiedByName": "AstoundOldUser",
      "lastModifiedDate": "2019-08-02T13:02:40.000Z",
      "manageableState": "unmanaged",
      "type": "Layout"
    },
    {
      "createdById": "0051U000005XFFIQA4",
      "createdByName": "AstoundOldUser",
      "createdDate": "2020-07-31T19:39:17.000Z",
      "fileName": "layouts/LiveChatVisitor-Chat Visitor Layout.layout",
      "fullName": "LiveChatVisitor-Chat Visitor Layout",
      "id": "00h1U000007pUGHQA2",
      "lastModifiedById": "0051U000005XFFIQA4",
      "lastModifiedByName": "AstoundOldUser",
      "lastModifiedDate": "2020-07-31T19:39:17.000Z",
      "manageableState": "unmanaged",
      "type": "Layout"
    },
    {
      "createdById": "0051U000005XFFIQA4",
      "createdByName": "AstoundOldUser",
      "createdDate": "2020-10-17T09:53:42.000Z",
      "fileName": "layouts/DelegatedAccount-External Managed Account Layout.layout",
      "fullName": "DelegatedAccount-External Managed Account Layout",
      "id": "00h1U000007QeC1QAK",
      "lastModifiedById": "0051U000005XFFIQA4",
      "lastModifiedByName": "AstoundOldUser",
      "lastModifiedDate": "2020-10-17T09:53:42.000Z",
      "manageableState": "unmanaged",
      "type": "Layout"
    },
    {
      "createdById": "0051U000001ugPnQAI",
      "createdByName": "Automated Process",
      "createdDate": "2018-12-19T20:27:32.000Z",
      "fileName": "layouts/QuickText-Quick Text Layout.layout",
      "fullName": "QuickText-Quick Text Layout",
      "id": "00h1U000002TMXWQA4",
      "lastModifiedById": "0051U000005tLLaQAM",
      "lastModifiedByName": "Toysrus AdminOldUser",
      "lastModifiedDate": "2020-09-24T19:21:46.000Z",
      "manageableState": "unmanaged",
      "type": "Layout"
    },
    {
      "createdById": "0051U000001ugPoQAI",
      "createdByName": "salesforce.com, inc.",
      "createdDate": "2018-12-19T20:27:32.000Z",
      "fileName": "layouts/UserAlt-User Profile Layout.layout",
      "fullName": "UserAlt-User Profile Layout",
      "id": "00h1U000002TMXGQA4",
      "lastModifiedById": "0051U000001L3PBQA0",
      "lastModifiedByName": "Craig Turner",
      "lastModifiedDate": "2018-12-19T20:27:32.000Z",
      "manageableState": "unmanaged",
      "type": "Layout"
    },
    {
      "createdById": "0051U000001ugPoQAI",
      "createdByName": "salesforce.com, inc.",
      "createdDate": "2018-12-19T20:27:32.000Z",
      "fileName": "layouts/EmailMessage-Email Message Layout.layout",
      "fullName": "EmailMessage-Email Message Layout",
      "id": "00h1U000002TMWuQAO",
      "lastModifiedById": "0051U000001ugPoQAI",
      "lastModifiedByName": "salesforce.com, inc.",
      "lastModifiedDate": "2018-12-19T20:27:32.000Z",
      "manageableState": "unmanaged",
      "type": "Layout"
    },
    {
      "createdById": "0051U000001L3PBQA0",
      "createdByName": "Craig Turner",
      "createdDate": "2018-12-19T20:27:32.000Z",
      "fileName": "layouts/Event-Event Layout.layout",
      "fullName": "Event-Event Layout",
      "id": "00h1U000002TMWmQAO",
      "lastModifiedById": "0051U000001L3PBQA0",
      "lastModifiedByName": "Craig Turner",
      "lastModifiedDate": "2018-12-19T20:27:53.000Z",
      "manageableState": "unmanaged",
      "type": "Layout"
    },
    {
      "createdById": "0051U000005XFFIQA4",
      "createdByName": "AstoundOldUser",
      "createdDate": "2019-06-20T14:47:20.000Z",
      "fileName": "layouts/et4ae5__MCOAuthClientDetail__mdt-MC OAuth Client Detail Layout.layout",
      "fullName": "et4ae5__MCOAuthClientDetail__mdt-MC OAuth Client Detail Layout",
      "id": "00h1U000007TT2WQAW",
      "lastModifiedById": "0051U000005XFFIQA4",
      "lastModifiedByName": "AstoundOldUser",
      "lastModifiedDate": "2019-06-20T14:47:48.000Z",
      "manageableState": "installed",
      "namespacePrefix": "et4ae5",
      "type": "Layout"
    },
    {
      "createdById": "0051U000001L3PBQA0",
      "createdByName": "Craig Turner",
      "createdDate": "2018-12-19T20:27:32.000Z",
      "fileName": "layouts/OrderItem-Order Product Layout.layout",
      "fullName": "OrderItem-Order Product Layout",
      "id": "00h1U000002TMX5QAO",
      "lastModifiedById": "0051U000001L3PBQA0",
      "lastModifiedByName": "Craig Turner",
      "lastModifiedDate": "2018-12-19T20:27:32.000Z",
      "manageableState": "unmanaged",
      "type": "Layout"
    },
    {
      "createdById": "0051U000008bjiLQAQ",
      "createdByName": "George Mahesh",
      "createdDate": "2022-03-01T15:04:23.000Z",
      "fileName": "layouts/Chat_URL__mdt-Chat URL Layout.layout",
      "fullName": "Chat_URL__mdt-Chat URL Layout",
      "id": "00h1U000007uTqkQAE",
      "lastModifiedById": "0051U000008bjiLQAQ",
      "lastModifiedByName": "George Mahesh",
      "lastModifiedDate": "2022-03-01T15:04:24.000Z",
      "manageableState": "unmanaged",
      "type": "Layout"
    },
    {
      "createdById": "0051U000005XFFIQA4",
      "createdByName": "AstoundOldUser",
      "createdDate": "2019-07-24T15:44:15.000Z",
      "fileName": "layouts/PersonAccount-SCC Person Account.layout",
      "fullName": "PersonAccount-SCC Person Account",
      "id": "00h1U000007FiXVQA0",
      "lastModifiedById": "0051U000008bjiLQAQ",
      "lastModifiedByName": "George Mahesh",
      "lastModifiedDate": "2022-05-12T14:55:19.000Z",
      "manageableState": "unmanaged",
      "type": "Layout"
    },
    {
      "createdById": "0051U000001L3PBQA0",
      "createdByName": "Craig Turner",
      "createdDate": "2018-12-19T20:27:32.000Z",
      "fileName": "layouts/Case-Case Layout.layout",
      "fullName": "Case-Case Layout",
      "id": "00h1U000002TMWqQAO",
      "lastModifiedById": "0051U0000060JrUQAU",
      "lastModifiedByName": "Christine Lamonde",
      "lastModifiedDate": "2022-06-06T19:54:08.000Z",
      "manageableState": "unmanaged",
      "type": "Layout"
    },
    {
      "createdById": "0051U000005XFFIQA4",
      "createdByName": "AstoundOldUser",
      "createdDate": "2019-06-20T14:47:18.000Z",
      "fileName": "layouts/et4ae5__Configuration__c-Configuration Layout.layout",
      "fullName": "et4ae5__Configuration__c-Configuration Layout",
      "id": "00h1U000007TT2SQAW",
      "lastModifiedById": "0051U000005XFFIQA4",
      "lastModifiedByName": "AstoundOldUser",
      "lastModifiedDate": "2019-06-20T14:47:48.000Z",
      "manageableState": "installed",
      "namespacePrefix": "et4ae5",
      "type": "Layout"
    },
    {
      "createdById": "0051U000005XFFIQA4",
      "createdByName": "AstoundOldUser",
      "createdDate": "2020-01-14T17:24:03.000Z",
      "fileName": "layouts/R_Club_Number__c-R Club Number Layout.layout",
      "fullName": "R_Club_Number__c-R Club Number Layout",
      "id": "00h1U000007ond5QAA",
      "lastModifiedById": "0051U000005XFFIQA4",
      "lastModifiedByName": "AstoundOldUser",
      "lastModifiedDate": "2020-01-14T17:24:07.000Z",
      "manageableState": "unmanaged",
      "type": "Layout"
    },
    {
      "createdById": "0051U000005tLLaQAM",
      "createdByName": "Toysrus AdminOldUser",
      "createdDate": "2020-10-19T13:25:22.000Z",
      "fileName": "layouts/lightningbuddy__Toaster_Alert_Param__c-Toaster Alert Param Layout.layout",
      "fullName": "lightningbuddy__Toaster_Alert_Param__c-Toaster Alert Param Layout",
      "id": "00h1U000007QfZZQA0",
      "lastModifiedById": "0051U000005tLLaQAM",
      "lastModifiedByName": "Toysrus AdminOldUser",
      "lastModifiedDate": "2020-10-19T13:25:33.000Z",
      "manageableState": "installed",
      "namespacePrefix": "lightningbuddy",
      "type": "Layout"
    },
    {
      "createdById": "0051U000005tLLaQAM",
      "createdByName": "Toysrus AdminOldUser",
      "createdDate": "2020-10-19T13:25:32.000Z",
      "fileName": "layouts/lightningbuddy__Actions__c-Image Carousel Actions Layout.layout",
      "fullName": "lightningbuddy__Actions__c-Image Carousel Actions Layout",
      "id": "00h1U000007QfZeQAK",
      "lastModifiedById": "0051U000005tLLaQAM",
      "lastModifiedByName": "Toysrus AdminOldUser",
      "lastModifiedDate": "2020-10-22T19:06:58.000Z",
      "manageableState": "installed",
      "namespacePrefix": "lightningbuddy",
      "type": "Layout"
    },
    {
      "createdById": "0051U000005XFFIQA4",
      "createdByName": "AstoundOldUser",
      "createdDate": "2019-06-20T14:47:20.000Z",
      "fileName": "layouts/et4ae5__SMSJunction__c-SMS Junction Layout.layout",
      "fullName": "et4ae5__SMSJunction__c-SMS Junction Layout",
      "id": "00h1U000007TT2YQAW",
      "lastModifiedById": "0051U000005XFFIQA4",
      "lastModifiedByName": "AstoundOldUser",
      "lastModifiedDate": "2019-06-20T14:47:47.000Z",
      "manageableState": "installed",
      "namespacePrefix": "et4ae5",
      "type": "Layout"
    },
    {
      "createdById": "0051U000001L3PBQA0",
      "createdByName": "Craig Turner",
      "createdDate": "2018-12-19T20:27:32.000Z",
      "fileName": "layouts/Scorecard-Scorecard Layout.layout",
      "fullName": "Scorecard-Scorecard Layout",
      "id": "00h1U000002TMXTQA4",
      "lastModifiedById": "0051U000001L3PBQA0",
      "lastModifiedByName": "Craig Turner",
      "lastModifiedDate": "2018-12-19T20:27:32.000Z",
      "manageableState": "unmanaged",
      "type": "Layout"
    },
    {
      "createdById": "0051U000001L3PBQA0",
      "createdByName": "Craig Turner",
      "createdDate": "2018-12-19T20:27:32.000Z",
      "fileName": "layouts/Task-Task Layout.layout",
      "fullName": "Task-Task Layout",
      "id": "00h1U000002TMWrQAO",
      "lastModifiedById": "0051U000001L3PBQA0",
      "lastModifiedByName": "Craig Turner",
      "lastModifiedDate": "2018-12-19T20:27:51.000Z",
      "manageableState": "unmanaged",
      "type": "Layout"
    },
    {
      "createdById": "0051U000005XFFIQA4",
      "createdByName": "AstoundOldUser",
      "createdDate": "2019-06-20T14:47:21.000Z",
      "fileName": "layouts/et4ae5__Triggered_Send_Execution__c-Triggered Send Execution Layout.layout",
      "fullName": "et4ae5__Triggered_Send_Execution__c-Triggered Send Execution Layout",
      "id": "00h1U000007TT2cQAG",
      "lastModifiedById": "0051U000005XFFIQA4",
      "lastModifiedByName": "AstoundOldUser",
      "lastModifiedDate": "2019-06-20T14:47:49.000Z",
      "manageableState": "installed",
      "namespacePrefix": "et4ae5",
      "type": "Layout"
    },
    {
      "createdById": "0051U000001L3PBQA0",
      "createdByName": "Craig Turner",
      "createdDate": "2018-12-19T20:27:32.000Z",
      "fileName": "layouts/Quote-Quote Layout.layout",
      "fullName": "Quote-Quote Layout",
      "id": "00h1U000002TMWvQAO",
      "lastModifiedById": "0051U000001L3PBQA0",
      "lastModifiedByName": "Craig Turner",
      "lastModifiedDate": "2018-12-19T20:27:32.000Z",
      "manageableState": "unmanaged",
      "type": "Layout"
    },
    {
      "createdById": "0051U000001ugPoQAI",
      "createdByName": "salesforce.com, inc.",
      "createdDate": "2021-10-09T05:02:35.000Z",
      "fileName": "layouts/Seller-Seller Layout.layout",
      "fullName": "Seller-Seller Layout",
      "id": "00h1U000007ZPvIQAW",
      "lastModifiedById": "0051U000001ugPoQAI",
      "lastModifiedByName": "salesforce.com, inc.",
      "lastModifiedDate": "2021-10-09T05:02:35.000Z",
      "manageableState": "unmanaged",
      "type": "Layout"
    },
    {
      "createdById": "0051U000005XFFIQA4",
      "createdByName": "AstoundOldUser",
      "createdDate": "2019-06-20T14:47:19.000Z",
      "fileName": "layouts/et4ae5__IndividualEmailResult__c-Individual Email Result Layout.layout",
      "fullName": "et4ae5__IndividualEmailResult__c-Individual Email Result Layout",
      "id": "00h1U000007TT2UQAW",
      "lastModifiedById": "0051U000005XFFIQA4",
      "lastModifiedByName": "AstoundOldUser",
      "lastModifiedDate": "2019-06-20T14:49:29.000Z",
      "manageableState": "installed",
      "namespacePrefix": "et4ae5",
      "type": "Layout"
    },
    {
      "createdById": "0051U000001ugPoQAI",
      "createdByName": "salesforce.com, inc.",
      "createdDate": "2022-01-17T15:53:11.000Z",
      "fileName": "layouts/SkillRequirement-Skill Requirement Layout.layout",
      "fullName": "SkillRequirement-Skill Requirement Layout",
      "id": "00h1U000007uSOGQA2",
      "lastModifiedById": "0051U000001ugPoQAI",
      "lastModifiedByName": "salesforce.com, inc.",
      "lastModifiedDate": "2022-01-17T15:53:11.000Z",
      "manageableState": "unmanaged",
      "type": "Layout"
    },
    {
      "createdById": "0051U000005XFFIQA4",
      "createdByName": "AstoundOldUser",
      "createdDate": "2019-06-20T14:47:18.000Z",
      "fileName": "layouts/et4ae5__Automated_Send__c-Active Send Layout.layout",
      "fullName": "et4ae5__Automated_Send__c-Active Send Layout",
      "id": "00h1U000007TT2PQAW",
      "lastModifiedById": "0051U000005XFFIQA4",
      "lastModifiedByName": "AstoundOldUser",
      "lastModifiedDate": "2019-06-20T14:49:29.000Z",
      "manageableState": "installed",
      "namespacePrefix": "et4ae5",
      "type": "Layout"
    },
    {
      "createdById": "0051U000005XFFIQA4",
      "createdByName": "AstoundOldUser",
      "createdDate": "2019-06-20T14:47:21.000Z",
      "fileName": "layouts/et4ae5__abTest__c-AB Test Layout.layout",
      "fullName": "et4ae5__abTest__c-AB Test Layout",
      "id": "00h1U000007TT2eQAG",
      "lastModifiedById": "0051U000005XFFIQA4",
      "lastModifiedByName": "AstoundOldUser",
      "lastModifiedDate": "2019-06-20T14:47:49.000Z",
      "manageableState": "installed",
      "namespacePrefix": "et4ae5",
      "type": "Layout"
    },
    {
      "createdById": "0051U000001ugPnQAI",
      "createdByName": "Automated Process",
      "createdDate": "2018-12-19T20:27:32.000Z",
      "fileName": "layouts/WorkBadgeDefinition-Badge Layout 192.layout",
      "fullName": "WorkBadgeDefinition-Badge Layout 192",
      "id": "00h1U000002TMXDQA4",
      "lastModifiedById": "0051U000001ugPnQAI",
      "lastModifiedByName": "Automated Process",
      "lastModifiedDate": "2018-12-19T20:27:32.000Z",
      "manageableState": "unmanaged",
      "type": "Layout"
    },
    {
      "createdById": "0051U000005XFFIQA4",
      "createdByName": "AstoundOldUser",
      "createdDate": "2019-06-20T14:47:18.000Z",
      "fileName": "layouts/et4ae5__Business_Unit__c-Business Unit Layout.layout",
      "fullName": "et4ae5__Business_Unit__c-Business Unit Layout",
      "id": "00h1U000007TT2QQAW",
      "lastModifiedById": "0051U000005XFFIQA4",
      "lastModifiedByName": "AstoundOldUser",
      "lastModifiedDate": "2019-06-20T14:47:48.000Z",
      "manageableState": "installed",
      "namespacePrefix": "et4ae5",
      "type": "Layout"
    },
    {
      "createdById": "0051U000001ugPoQAI",
      "createdByName": "salesforce.com, inc.",
      "createdDate": "2018-12-19T20:27:32.000Z",
      "fileName": "layouts/FeedItem-Feed Item Layout.layout",
      "fullName": "FeedItem-Feed Item Layout",
      "id": "00h1U000002TMXPQA4",
      "lastModifiedById": "0051U000001ugPoQAI",
      "lastModifiedByName": "salesforce.com, inc.",
      "lastModifiedDate": "2018-12-19T20:27:32.000Z",
      "manageableState": "unmanaged",
      "type": "Layout"
    },
    {
      "createdById": "0051U000001ugPoQAI",
      "createdByName": "salesforce.com, inc.",
      "createdDate": "2022-03-01T19:30:45.000Z",
      "fileName": "layouts/SurveyVersion-Survey Version Layout.layout",
      "fullName": "SurveyVersion-Survey Version Layout",
      "id": "00h1U000007uTrEQAU",
      "lastModifiedById": "0051U000001ugPoQAI",
      "lastModifiedByName": "salesforce.com, inc.",
      "lastModifiedDate": "2022-03-01T19:30:45.000Z",
      "manageableState": "unmanaged",
      "type": "Layout"
    },
    {
      "createdById": "0051U000005XFFIQA4",
      "createdByName": "AstoundOldUser",
      "createdDate": "2020-07-31T19:39:17.000Z",
      "fileName": "layouts/LiveChatTranscriptActive-Chat Transcript %28In Progress%29 Layout.layout",
      "fullName": "LiveChatTranscriptActive-Chat Transcript %28In Progress%29 Layout",
      "id": "00h1U000007pUGJQA2",
      "lastModifiedById": "0051U000005XFFIQA4",
      "lastModifiedByName": "AstoundOldUser",
      "lastModifiedDate": "2020-07-31T19:39:17.000Z",
      "manageableState": "unmanaged",
      "type": "Layout"
    },
    {
      "createdById": "0051U000001L3PBQA0",
      "createdByName": "Craig Turner",
      "createdDate": "2018-12-19T20:27:32.000Z",
      "fileName": "layouts/WorkThanks-Thanks Layout.layout",
      "fullName": "WorkThanks-Thanks Layout",
      "id": "00h1U000002TMXAQA4",
      "lastModifiedById": "0051U000001L3PBQA0",
      "lastModifiedByName": "Craig Turner",
      "lastModifiedDate": "2018-12-19T20:27:32.000Z",
      "manageableState": "unmanaged",
      "type": "Layout"
    },
    {
      "createdById": "0051U000001ugPoQAI",
      "createdByName": "salesforce.com, inc.",
      "createdDate": "2022-04-24T22:10:57.000Z",
      "fileName": "layouts/SurveyQuestionResponse-Survey Question Response Layout.layout",
      "fullName": "SurveyQuestionResponse-Survey Question Response Layout",
      "id": "00h8Z00000SOv0CQAT",
      "lastModifiedById": "0051U000001ugPoQAI",
      "lastModifiedByName": "salesforce.com, inc.",
      "lastModifiedDate": "2022-04-24T22:10:57.000Z",
      "manageableState": "unmanaged",
      "type": "Layout"
    },
    {
      "createdById": "0051U000001ugPoQAI",
      "createdByName": "salesforce.com, inc.",
      "createdDate": "2018-12-19T20:27:32.000Z",
      "fileName": "layouts/CollaborationGroup-Group Layout.layout",
      "fullName": "CollaborationGroup-Group Layout",
      "id": "00h1U000002TMWiQAO",
      "lastModifiedById": "0051U000001L3PBQA0",
      "lastModifiedByName": "Craig Turner",
      "lastModifiedDate": "2018-12-19T20:27:32.000Z",
      "manageableState": "unmanaged",
      "type": "Layout"
    },
    {
      "createdById": "0051U000001L3PBQA0",
      "createdByName": "Craig Turner",
      "createdDate": "2018-12-19T20:27:32.000Z",
      "fileName": "layouts/Account-Account Layout.layout",
      "fullName": "Account-Account Layout",
      "id": "00h1U000002TMWjQAO",
      "lastModifiedById": "0051U000008bjiLQAQ",
      "lastModifiedByName": "George Mahesh",
      "lastModifiedDate": "2021-08-03T12:43:26.000Z",
      "manageableState": "unmanaged",
      "type": "Layout"
    },
    {
      "createdById": "0051U000005XLyGQAW",
      "createdByName": "MCIntegrationOldUser",
      "createdDate": "2020-02-21T20:53:17.000Z",
      "fileName": "layouts/ContactPointPhone-Contact Point Phone Layout.layout",
      "fullName": "ContactPointPhone-Contact Point Phone Layout",
      "id": "00h1U000007ouNuQAI",
      "lastModifiedById": "0051U000005XLyGQAW",
      "lastModifiedByName": "MCIntegrationOldUser",
      "lastModifiedDate": "2020-02-21T20:53:17.000Z",
      "manageableState": "unmanaged",
      "type": "Layout"
    },
    {
      "createdById": "0051U000001ugPnQAI",
      "createdByName": "Automated Process",
      "createdDate": "2020-07-18T07:07:44.000Z",
      "fileName": "layouts/ContactPointAddress-Contact Point Address Layout.layout",
      "fullName": "ContactPointAddress-Contact Point Address Layout",
      "id": "00h1U000007pJdtQAE",
      "lastModifiedById": "0051U000001ugPnQAI",
      "lastModifiedByName": "Automated Process",
      "lastModifiedDate": "2020-07-18T07:07:44.000Z",
      "manageableState": "unmanaged",
      "type": "Layout"
    },
    {
      "createdById": "0051U000005XFFIQA4",
      "createdByName": "AstoundOldUser",
      "createdDate": "2019-06-20T14:47:19.000Z",
      "fileName": "layouts/et4ae5__IndividualLink__c-Individual Link Level Detail Layout.layout",
      "fullName": "et4ae5__IndividualLink__c-Individual Link Level Detail Layout",
      "id": "00h1U000007TT2VQAW",
      "lastModifiedById": "0051U000005XFFIQA4",
      "lastModifiedByName": "AstoundOldUser",
      "lastModifiedDate": "2019-06-20T14:47:48.000Z",
      "manageableState": "installed",
      "namespacePrefix": "et4ae5",
      "type": "Layout"
    },
    {
      "createdById": "0051U000005XFFIQA4",
      "createdByName": "AstoundOldUser",
      "createdDate": "2019-08-01T08:59:21.000Z",
      "fileName": "layouts/Order_Line_Item__c-Order Line Item Layout.layout",
      "fullName": "Order_Line_Item__c-Order Line Item Layout",
      "id": "00h1U000007FjZPQA0",
      "lastModifiedById": "0051U000005XFFIQA4",
      "lastModifiedByName": "AstoundOldUser",
      "lastModifiedDate": "2019-08-21T15:51:15.000Z",
      "manageableState": "unmanaged",
      "type": "Layout"
    },
    {
      "createdById": "0051U000001ugPoQAI",
      "createdByName": "salesforce.com, inc.",
      "createdDate": "2018-12-19T20:27:32.000Z",
      "fileName": "layouts/SocialPost-Social Post Layout.layout",
      "fullName": "SocialPost-Social Post Layout",
      "id": "00h1U000002TMWxQAO",
      "lastModifiedById": "0051U000001ugPoQAI",
      "lastModifiedByName": "salesforce.com, inc.",
      "lastModifiedDate": "2018-12-19T20:27:32.000Z",
      "manageableState": "unmanaged",
      "type": "Layout"
    },
    {
      "createdById": "0051U000001L3PBQA0",
      "createdByName": "Craig Turner",
      "createdDate": "2018-12-19T20:27:32.000Z",
      "fileName": "layouts/Contact-Contact Layout.layout",
      "fullName": "Contact-Contact Layout",
      "id": "00h1U000002TMWkQAO",
      "lastModifiedById": "0051U000005tLLaQAM",
      "lastModifiedByName": "Toysrus AdminOldUser",
      "lastModifiedDate": "2021-02-18T15:49:40.000Z",
      "manageableState": "unmanaged",
      "type": "Layout"
    },
    {
      "createdById": "0051U000001ugPoQAI",
      "createdByName": "salesforce.com, inc.",
      "createdDate": "2022-03-01T19:30:31.000Z",
      "fileName": "layouts/Survey-Survey Layout.layout",
      "fullName": "Survey-Survey Layout",
      "id": "00h1U000007uTr9QAE",
      "lastModifiedById": "0051U000001ugPoQAI",
      "lastModifiedByName": "salesforce.com, inc.",
      "lastModifiedDate": "2022-03-01T19:30:31.000Z",
      "manageableState": "unmanaged",
      "type": "Layout"
    },
    {
      "createdById": "0051U000005XFFIQA4",
      "createdByName": "AstoundOldUser",
      "createdDate": "2019-06-20T14:47:18.000Z",
      "fileName": "layouts/et4ae5__Email_Linkage__c-Email Linkage Layout.layout",
      "fullName": "et4ae5__Email_Linkage__c-Email Linkage Layout",
      "id": "00h1U000007TT2TQAW",
      "lastModifiedById": "0051U000005XFFIQA4",
      "lastModifiedByName": "AstoundOldUser",
      "lastModifiedDate": "2019-06-20T14:47:48.000Z",
      "manageableState": "installed",
      "namespacePrefix": "et4ae5",
      "type": "Layout"
    },
    {
      "createdById": "0051U000005XFFIQA4",
      "createdByName": "AstoundOldUser",
      "createdDate": "2019-08-02T09:45:39.000Z",
      "fileName": "layouts/Case-Price Match.layout",
      "fullName": "Case-Price Match",
      "id": "00h1U000007Fji1QAC",
      "lastModifiedById": "0051U0000060JrUQAU",
      "lastModifiedByName": "Christine Lamonde",
      "lastModifiedDate": "2022-06-06T19:54:08.000Z",
      "manageableState": "unmanaged",
      "type": "Layout"
    },
    {
      "createdById": "0051U000005XLwAQAW",
      "createdByName": "Marketing Cloud",
      "createdDate": "2020-10-31T13:01:56.000Z",
      "fileName": "layouts/et4ae5__Journey__c-Journey Layout.layout",
      "fullName": "et4ae5__Journey__c-Journey Layout",
      "id": "00h1U000007QhTZQA0",
      "lastModifiedById": "0051U000005XLwAQAW",
      "lastModifiedByName": "Marketing Cloud",
      "lastModifiedDate": "2020-10-31T13:02:11.000Z",
      "manageableState": "installed",
      "namespacePrefix": "et4ae5",
      "type": "Layout"
    },
    {
      "createdById": "0051U000005tLLaQAM",
      "createdByName": "Toysrus AdminOldUser",
      "createdDate": "2020-10-19T13:25:32.000Z",
      "fileName": "layouts/lightningbuddy__Actions__c-Rich Text Actions Layout.layout",
      "fullName": "lightningbuddy__Actions__c-Rich Text Actions Layout",
      "id": "00h1U000007QfZhQAK",
      "lastModifiedById": "0051U000005tLLaQAM",
      "lastModifiedByName": "Toysrus AdminOldUser",
      "lastModifiedDate": "2020-10-22T19:17:11.000Z",
      "manageableState": "installed",
      "namespacePrefix": "lightningbuddy",
      "type": "Layout"
    },
    {
      "createdById": "0051U000005tLLaQAM",
      "createdByName": "Toysrus AdminOldUser",
      "createdDate": "2020-10-19T13:25:22.000Z",
      "fileName": "layouts/lightningbuddy__Welcome_Mat_Tile__c-Welcome Mat Tile Layout.layout",
      "fullName": "lightningbuddy__Welcome_Mat_Tile__c-Welcome Mat Tile Layout",
      "id": "00h1U000007QfZbQAK",
      "lastModifiedById": "0051U000005tLLaQAM",
      "lastModifiedByName": "Toysrus AdminOldUser",
      "lastModifiedDate": "2020-10-19T13:25:33.000Z",
      "manageableState": "installed",
      "namespacePrefix": "lightningbuddy",
      "type": "Layout"
    },
    {
      "createdById": "0051U000001L3PBQA0",
      "createdByName": "Craig Turner",
      "createdDate": "2018-12-19T20:27:32.000Z",
      "fileName": "layouts/ProfileSkill-Skill Layout.layout",
      "fullName": "ProfileSkill-Skill Layout",
      "id": "00h1U000002TMXHQA4",
      "lastModifiedById": "0051U000001L3PBQA0",
      "lastModifiedByName": "Craig Turner",
      "lastModifiedDate": "2018-12-19T20:27:32.000Z",
      "manageableState": "unmanaged",
      "type": "Layout"
    },
    {
      "createdById": "0051U000005tLLaQAM",
      "createdByName": "Toysrus AdminOldUser",
      "createdDate": "2020-10-19T13:25:22.000Z",
      "fileName": "layouts/lightningbuddy__Url_Path_Mapping__mdt-Url Path Mapping Layout.layout",
      "fullName": "lightningbuddy__Url_Path_Mapping__mdt-Url Path Mapping Layout",
      "id": "00h1U000007QfZaQAK",
      "lastModifiedById": "0051U000005tLLaQAM",
      "lastModifiedByName": "Toysrus AdminOldUser",
      "lastModifiedDate": "2020-10-19T13:25:33.000Z",
      "manageableState": "installed",
      "namespacePrefix": "lightningbuddy",
      "type": "Layout"
    },
    {
      "createdById": "0051U000001L3PBQA0",
      "createdByName": "Craig Turner",
      "createdDate": "2018-12-19T20:27:32.000Z",
      "fileName": "layouts/WorkAccess-Access Layout.layout",
      "fullName": "WorkAccess-Access Layout",
      "id": "00h1U000002TMXBQA4",
      "lastModifiedById": "0051U000001L3PBQA0",
      "lastModifiedByName": "Craig Turner",
      "lastModifiedDate": "2018-12-19T20:27:32.000Z",
      "manageableState": "unmanaged",
      "type": "Layout"
    },
    {
      "createdById": "0051U000005XFFIQA4",
      "createdByName": "AstoundOldUser",
      "createdDate": "2019-06-20T14:47:17.000Z",
      "fileName": "layouts/et4ae5__AggregateLink__c-Aggregate Link Level Detail Layout.layout",
      "fullName": "et4ae5__AggregateLink__c-Aggregate Link Level Detail Layout",
      "id": "00h1U000007TT2OQAW",
      "lastModifiedById": "0051U000005XFFIQA4",
      "lastModifiedByName": "AstoundOldUser",
      "lastModifiedDate": "2019-06-20T14:47:47.000Z",
      "manageableState": "installed",
      "namespacePrefix": "et4ae5",
      "type": "Layout"
    },
    {
      "createdById": "0051U000005XFFIQA4",
      "createdByName": "AstoundOldUser",
      "createdDate": "2019-06-20T14:47:20.000Z",
      "fileName": "layouts/et4ae5__SMSDefinition__c-Mobile Send Layout.layout",
      "fullName": "et4ae5__SMSDefinition__c-Mobile Send Layout",
      "id": "00h1U000007TT2XQAW",
      "lastModifiedById": "0051U000005XFFIQA4",
      "lastModifiedByName": "AstoundOldUser",
      "lastModifiedDate": "2019-06-20T14:49:30.000Z",
      "manageableState": "installed",
      "namespacePrefix": "et4ae5",
      "type": "Layout"
    },
    {
      "createdById": "0051U000001ugPoQAI",
      "createdByName": "salesforce.com, inc.",
      "createdDate": "2020-07-18T07:07:35.000Z",
      "fileName": "layouts/UserProvisioningRequest-User Provisioning Request Layout.layout",
      "fullName": "UserProvisioningRequest-User Provisioning Request Layout",
      "id": "00h1U000007pJdqQAE",
      "lastModifiedById": "0051U000001ugPoQAI",
      "lastModifiedByName": "salesforce.com, inc.",
      "lastModifiedDate": "2020-07-18T07:07:35.000Z",
      "manageableState": "unmanaged",
      "type": "Layout"
    },
    {
      "createdById": "0051U000001L3PBQA0",
      "createdByName": "Craig Turner",
      "createdDate": "2018-12-19T20:27:32.000Z",
      "fileName": "layouts/WorkBadgeDefinition-Badge Definition Layout.layout",
      "fullName": "WorkBadgeDefinition-Badge Definition Layout",
      "id": "00h1U000002TMXNQA4",
      "lastModifiedById": "0051U000001L3PBQA0",
      "lastModifiedByName": "Craig Turner",
      "lastModifiedDate": "2018-12-19T20:27:32.000Z",
      "manageableState": "unmanaged",
      "type": "Layout"
    },
    {
      "createdById": "0051U000001ugPoQAI",
      "createdByName": "salesforce.com, inc.",
      "createdDate": "2020-10-20T17:20:01.000Z",
      "fileName": "layouts/Location-Location Layout.layout",
      "fullName": "Location-Location Layout",
      "id": "00h1U000007QfmoQAC",
      "lastModifiedById": "0051U000001ugPoQAI",
      "lastModifiedByName": "salesforce.com, inc.",
      "lastModifiedDate": "2020-10-20T17:20:01.000Z",
      "manageableState": "unmanaged",
      "type": "Layout"
    },
    {
      "createdById": "0051U000001L3PBQA0",
      "createdByName": "Craig Turner",
      "createdDate": "2018-12-19T20:27:32.000Z",
      "fileName": "layouts/Campaign-Campaign Layout.layout",
      "fullName": "Campaign-Campaign Layout",
      "id": "00h1U000002TMWpQAO",
      "lastModifiedById": "0051U000001L3PBQA0",
      "lastModifiedByName": "Craig Turner",
      "lastModifiedDate": "2018-12-19T20:27:51.000Z",
      "manageableState": "unmanaged",
      "type": "Layout"
    },
    {
      "createdById": "0051U000001ugPnQAI",
      "createdByName": "Automated Process",
      "createdDate": "2018-12-19T20:27:32.000Z",
      "fileName": "layouts/WorkBadge-Badge Received Layout 192.layout",
      "fullName": "WorkBadge-Badge Received Layout 192",
      "id": "00h1U000002TMXEQA4",
      "lastModifiedById": "0051U000001ugPnQAI",
      "lastModifiedByName": "Automated Process",
      "lastModifiedDate": "2018-12-19T20:27:32.000Z",
      "manageableState": "unmanaged",
      "type": "Layout"
    },
    {
      "createdById": "0051U000005tLLaQAM",
      "createdByName": "Toysrus AdminOldUser",
      "createdDate": "2020-10-19T13:25:32.000Z",
      "fileName": "layouts/lightningbuddy__Actions__c-Toaster Alert Actions Layout.layout",
      "fullName": "lightningbuddy__Actions__c-Toaster Alert Actions Layout",
      "id": "00h1U000007QfZiQAK",
      "lastModifiedById": "0051U000005tLLaQAM",
      "lastModifiedByName": "Toysrus AdminOldUser",
      "lastModifiedDate": "2020-10-22T19:06:58.000Z",
      "manageableState": "installed",
      "namespacePrefix": "lightningbuddy",
      "type": "Layout"
    },
    {
      "createdById": "0051U000005XFFIQA4",
      "createdByName": "AstoundOldUser",
      "createdDate": "2019-08-22T17:47:15.000Z",
      "fileName": "layouts/Registry__c-Registry Layout.layout",
      "fullName": "Registry__c-Registry Layout",
      "id": "00h1U000007FoqiQAC",
      "lastModifiedById": "0051U000005XFFIQA4",
      "lastModifiedByName": "AstoundOldUser",
      "lastModifiedDate": "2019-12-05T14:37:04.000Z",
      "manageableState": "unmanaged",
      "type": "Layout"
    },
    {
      "createdById": "0051U000001L3PBQA0",
      "createdByName": "Craig Turner",
      "createdDate": "2018-12-19T20:27:32.000Z",
      "fileName": "layouts/OpportunityLineItem-Opportunity Product Layout.layout",
      "fullName": "OpportunityLineItem-Opportunity Product Layout",
      "id": "00h1U000002TMX3QAO",
      "lastModifiedById": "0051U000001L3PBQA0",
      "lastModifiedByName": "Craig Turner",
      "lastModifiedDate": "2018-12-19T20:27:32.000Z",
      "manageableState": "unmanaged",
      "type": "Layout"
    },
    {
      "createdById": "0051U000005tLLaQAM",
      "createdByName": "Toysrus AdminOldUser",
      "createdDate": "2020-10-19T13:25:32.000Z",
      "fileName": "layouts/lightningbuddy__Actions__c-Popover Actions Layout.layout",
      "fullName": "lightningbuddy__Actions__c-Popover Actions Layout",
      "id": "00h1U000007QfZgQAK",
      "lastModifiedById": "0051U000005tLLaQAM",
      "lastModifiedByName": "Toysrus AdminOldUser",
      "lastModifiedDate": "2020-10-22T19:06:58.000Z",
      "manageableState": "installed",
      "namespacePrefix": "lightningbuddy",
      "type": "Layout"
    },
    {
      "createdById": "0051U000001ugPnQAI",
      "createdByName": "Automated Process",
      "createdDate": "2018-12-19T20:27:32.000Z",
      "fileName": "layouts/Pricebook2-Price Book Layout.layout",
      "fullName": "Pricebook2-Price Book Layout",
      "id": "00h1U000002TMX9QAO",
      "lastModifiedById": "0051U000001ugPnQAI",
      "lastModifiedByName": "Automated Process",
      "lastModifiedDate": "2018-12-19T20:27:32.000Z",
      "manageableState": "unmanaged",
      "type": "Layout"
    },
    {
      "createdById": "0051U000005XFFIQA4",
      "createdByName": "AstoundOldUser",
      "createdDate": "2019-08-02T09:49:08.000Z",
      "fileName": "layouts/Case-In Store Case.layout",
      "fullName": "Case-In Store Case",
      "id": "00h1U000007FjiGQAS",
      "lastModifiedById": "0051U0000060JrUQAU",
      "lastModifiedByName": "Christine Lamonde",
      "lastModifiedDate": "2022-06-06T19:54:08.000Z",
      "manageableState": "unmanaged",
      "type": "Layout"
    },
    {
      "createdById": "0051U000001ugPoQAI",
      "createdByName": "salesforce.com, inc.",
      "createdDate": "2022-04-11T16:05:11.000Z",
      "fileName": "layouts/SurveyQuestionChoice-Survey Question Choice Layout.layout",
      "fullName": "SurveyQuestionChoice-Survey Question Choice Layout",
      "id": "00h8Z00000SOuv7QAD",
      "lastModifiedById": "0051U000001ugPoQAI",
      "lastModifiedByName": "salesforce.com, inc.",
      "lastModifiedDate": "2022-04-11T16:05:11.000Z",
      "manageableState": "unmanaged",
      "type": "Layout"
    },
    {
      "createdById": "0051U000001ugPoQAI",
      "createdByName": "salesforce.com, inc.",
      "createdDate": "2018-12-19T20:27:32.000Z",
      "fileName": "layouts/AssetRelationship-Asset Relationship Layout.layout",
      "fullName": "AssetRelationship-Asset Relationship Layout",
      "id": "00h1U000002TMWwQAO",
      "lastModifiedById": "0051U000001ugPoQAI",
      "lastModifiedByName": "salesforce.com, inc.",
      "lastModifiedDate": "2018-12-19T20:27:32.000Z",
      "manageableState": "unmanaged",
      "type": "Layout"
    },
    {
      "createdById": "0051U000001ugPoQAI",
      "createdByName": "salesforce.com, inc.",
      "createdDate": "2018-12-19T20:27:32.000Z",
      "fileName": "layouts/Macro-Macro Layout.layout",
      "fullName": "Macro-Macro Layout",
      "id": "00h1U000002TMXSQA4",
      "lastModifiedById": "0051U0000060JrUQAU",
      "lastModifiedByName": "Christine Lamonde",
      "lastModifiedDate": "2021-04-09T17:04:58.000Z",
      "manageableState": "unmanaged",
      "type": "Layout"
    },
    {
      "createdById": "0051U000001ugPoQAI",
      "createdByName": "salesforce.com, inc.",
      "createdDate": "2021-04-09T03:50:05.000Z",
      "fileName": "layouts/ProcessException-Process Exception Layout.layout",
      "fullName": "ProcessException-Process Exception Layout",
      "id": "00h1U000007tyKrQAI",
      "lastModifiedById": "0051U000001ugPoQAI",
      "lastModifiedByName": "salesforce.com, inc.",
      "lastModifiedDate": "2021-04-09T03:50:05.000Z",
      "manageableState": "unmanaged",
      "type": "Layout"
    },
    {
      "createdById": "0051U000005XFFIQA4",
      "createdByName": "AstoundOldUser",
      "createdDate": "2019-08-01T08:59:21.000Z",
      "fileName": "layouts/Shipment__c-Shipment Layout.layout",
      "fullName": "Shipment__c-Shipment Layout",
      "id": "00h1U000007FjZRQA0",
      "lastModifiedById": "0051U000005XFFIQA4",
      "lastModifiedByName": "AstoundOldUser",
      "lastModifiedDate": "2019-08-21T15:51:15.000Z",
      "manageableState": "unmanaged",
      "type": "Layout"
    },
    {
      "createdById": "0051U000001L3PBQA0",
      "createdByName": "Craig Turner",
      "createdDate": "2018-12-19T20:27:32.000Z",
      "fileName": "layouts/ContentVersion-Content Version.layout",
      "fullName": "ContentVersion-Content Version",
      "id": "00h1U000002TMXQQA4",
      "lastModifiedById": "0051U000001L3PBQA0",
      "lastModifiedByName": "Craig Turner",
      "lastModifiedDate": "2018-12-19T20:27:32.000Z",
      "manageableState": "unmanaged",
      "type": "Layout"
    },
    {
      "createdById": "0051U000005XFFIQA4",
      "createdByName": "AstoundOldUser",
      "createdDate": "2019-06-20T14:47:18.000Z",
      "fileName": "layouts/et4ae5__Campaign_Member_Configuration__c-Campaign Member Configuration Layout.layout",
      "fullName": "et4ae5__Campaign_Member_Configuration__c-Campaign Member Configuration Layout",
      "id": "00h1U000007TT2RQAW",
      "lastModifiedById": "0051U000005XFFIQA4",
      "lastModifiedByName": "AstoundOldUser",
      "lastModifiedDate": "2019-06-20T14:47:48.000Z",
      "manageableState": "installed",
      "namespacePrefix": "et4ae5",
      "type": "Layout"
    },
    {
      "createdById": "0051U000005XFFIQA4",
      "createdByName": "AstoundOldUser",
      "createdDate": "2020-07-31T19:39:17.000Z",
      "fileName": "layouts/LiveChatTranscriptWaiting-Chat Transcript %28Waiting%29 Layout.layout",
      "fullName": "LiveChatTranscriptWaiting-Chat Transcript %28Waiting%29 Layout",
      "id": "00h1U000007pUGIQA2",
      "lastModifiedById": "0051U000005XFFIQA4",
      "lastModifiedByName": "AstoundOldUser",
      "lastModifiedDate": "2020-07-31T19:39:17.000Z",
      "manageableState": "unmanaged",
      "type": "Layout"
    },
    {
      "createdById": "0051U000001ugPnQAI",
      "createdByName": "Automated Process",
      "createdDate": "2018-12-19T20:27:32.000Z",
      "fileName": "layouts/ScorecardAssociation-Scorecard Association Layout.layout",
      "fullName": "ScorecardAssociation-Scorecard Association Layout",
      "id": "00h1U000002TMXVQA4",
      "lastModifiedById": "0051U000001ugPnQAI",
      "lastModifiedByName": "Automated Process",
      "lastModifiedDate": "2018-12-19T20:27:32.000Z",
      "manageableState": "unmanaged",
      "type": "Layout"
    },
    {
      "createdById": "0051U000005tLLaQAM",
      "createdByName": "Toysrus AdminOldUser",
      "createdDate": "2020-09-16T05:21:26.000Z",
      "fileName": "layouts/Manufacturer__c-Manufacturer Layout.layout",
      "fullName": "Manufacturer__c-Manufacturer Layout",
      "id": "00h1U000007tQUnQAM",
      "lastModifiedById": "0051U000005tLLaQAM",
      "lastModifiedByName": "Toysrus AdminOldUser",
      "lastModifiedDate": "2020-09-16T05:21:41.000Z",
      "manageableState": "unmanaged",
      "type": "Layout"
    },
    {
      "createdById": "0051U000005tLLaQAM",
      "createdByName": "Toysrus AdminOldUser",
      "createdDate": "2020-10-19T13:25:32.000Z",
      "fileName": "layouts/lightningbuddy__Actions__c-Object Quick Action Layout.layout",
      "fullName": "lightningbuddy__Actions__c-Object Quick Action Layout",
      "id": "00h1U000007QfZfQAK",
      "lastModifiedById": "0051U000005tLLaQAM",
      "lastModifiedByName": "Toysrus AdminOldUser",
      "lastModifiedDate": "2020-10-22T19:06:58.000Z",
      "manageableState": "installed",
      "namespacePrefix": "lightningbuddy",
      "type": "Layout"
    },
    {
      "createdById": "0051U000005XFFIQA4",
      "createdByName": "AstoundOldUser",
      "createdDate": "2019-06-20T14:47:49.000Z",
      "fileName": "layouts/et4ae5__SendDefinition__c-Trackable Send Definition Layout new.layout",
      "fullName": "et4ae5__SendDefinition__c-Trackable Send Definition Layout new",
      "id": "00h1U000007TT2kQAG",
      "lastModifiedById": "0051U000005XFFIQA4",
      "lastModifiedByName": "AstoundOldUser",
      "lastModifiedDate": "2019-06-20T14:49:30.000Z",
      "manageableState": "installed",
      "namespacePrefix": "et4ae5",
      "type": "Layout"
    },
    {
      "createdById": "0051U000005tLLaQAM",
      "createdByName": "Toysrus AdminOldUser",
      "createdDate": "2020-09-16T05:21:26.000Z",
      "fileName": "layouts/Queue_Sub_Type_w_Disposition__mdt-Queue Sub Type w%2F Disposition Layout.layout",
      "fullName": "Queue_Sub_Type_w_Disposition__mdt-Queue Sub Type w%2F Disposition Layout",
      "id": "00h1U000007tQUoQAM",
      "lastModifiedById": "0051U000005tLLaQAM",
      "lastModifiedByName": "Toysrus AdminOldUser",
      "lastModifiedDate": "2020-09-16T05:21:42.000Z",
      "manageableState": "unmanaged",
      "type": "Layout"
    },
    {
      "createdById": "0051U000001L3PBQA0",
      "createdByName": "Craig Turner",
      "createdDate": "2018-12-19T20:27:32.000Z",
      "fileName": "layouts/Contract-Contract Layout.layout",
      "fullName": "Contract-Contract Layout",
      "id": "00h1U000002TMX1QAO",
      "lastModifiedById": "0051U000001L3PBQA0",
      "lastModifiedByName": "Craig Turner",
      "lastModifiedDate": "2018-12-19T20:27:32.000Z",
      "manageableState": "unmanaged",
      "type": "Layout"
    },
    {
      "createdById": "0051U000005XFFIQA4",
      "createdByName": "AstoundOldUser",
      "createdDate": "2020-07-31T19:39:16.000Z",
      "fileName": "layouts/LiveAgentSession-Chat Session Layout.layout",
      "fullName": "LiveAgentSession-Chat Session Layout",
      "id": "00h1U000007pUGEQA2",
      "lastModifiedById": "0051U000005XFFIQA4",
      "lastModifiedByName": "AstoundOldUser",
      "lastModifiedDate": "2020-07-31T19:39:16.000Z",
      "manageableState": "unmanaged",
      "type": "Layout"
    },
    {
      "createdById": "0051U000001ugPoQAI",
      "createdByName": "salesforce.com, inc.",
      "createdDate": "2020-07-18T07:07:35.000Z",
      "fileName": "layouts/UserProvisioningLog-User Provisioning Log Layout.layout",
      "fullName": "UserProvisioningLog-User Provisioning Log Layout",
      "id": "00h1U000007pJdrQAE",
      "lastModifiedById": "0051U000001ugPoQAI",
      "lastModifiedByName": "salesforce.com, inc.",
      "lastModifiedDate": "2020-07-18T07:07:35.000Z",
      "manageableState": "unmanaged",
      "type": "Layout"
    },
    {
      "createdById": "0051U000005tLLaQAM",
      "createdByName": "Toysrus AdminOldUser",
      "createdDate": "2020-10-19T13:25:22.000Z",
      "fileName": "layouts/lightningbuddy__Action_User_Preference__c-Action User Preference Layout.layout",
      "fullName": "lightningbuddy__Action_User_Preference__c-Action User Preference Layout",
      "id": "00h1U000007QfZVQA0",
      "lastModifiedById": "0051U000005tLLaQAM",
      "lastModifiedByName": "Toysrus AdminOldUser",
      "lastModifiedDate": "2020-10-19T13:25:31.000Z",
      "manageableState": "installed",
      "namespacePrefix": "lightningbuddy",
      "type": "Layout"
    },
    {
      "createdById": "0051U000001ugPoQAI",
      "createdByName": "salesforce.com, inc.",
      "createdDate": "2020-09-10T18:20:09.000Z",
      "fileName": "layouts/DuplicateRecordItem-Duplicate Record Item Layout.layout",
      "fullName": "DuplicateRecordItem-Duplicate Record Item Layout",
      "id": "00h1U000007tPxrQAE",
      "lastModifiedById": "0051U000001ugPnQAI",
      "lastModifiedByName": "Automated Process",
      "lastModifiedDate": "2021-07-09T05:34:13.000Z",
      "manageableState": "unmanaged",
      "type": "Layout"
    },
    {
      "createdById": "0051U000001L3PBQA0",
      "createdByName": "Craig Turner",
      "createdDate": "2018-12-19T20:27:32.000Z",
      "fileName": "layouts/WorkBadge-Badge Layout.layout",
      "fullName": "WorkBadge-Badge Layout",
      "id": "00h1U000002TMXMQA4",
      "lastModifiedById": "0051U000001L3PBQA0",
      "lastModifiedByName": "Craig Turner",
      "lastModifiedDate": "2018-12-19T20:27:32.000Z",
      "manageableState": "unmanaged",
      "type": "Layout"
    },
    {
      "createdById": "0051U000001L3PBQA0",
      "createdByName": "Craig Turner",
      "createdDate": "2018-12-19T20:27:32.000Z",
      "fileName": "layouts/Product2-Product Layout.layout",
      "fullName": "Product2-Product Layout",
      "id": "00h1U000002TMWsQAO",
      "lastModifiedById": "0051U000001L3PBQA0",
      "lastModifiedByName": "Craig Turner",
      "lastModifiedDate": "2018-12-19T20:27:32.000Z",
      "manageableState": "unmanaged",
      "type": "Layout"
    },
    {
      "createdById": "0051U000005tLLaQAM",
      "createdByName": "Toysrus AdminOldUser",
      "createdDate": "2020-10-19T13:25:32.000Z",
      "fileName": "layouts/lightningbuddy__Actions__c-Video Actions Layout.layout",
      "fullName": "lightningbuddy__Actions__c-Video Actions Layout",
      "id": "00h1U000007QfZjQAK",
      "lastModifiedById": "0051U000005tLLaQAM",
      "lastModifiedByName": "Toysrus AdminOldUser",
      "lastModifiedDate": "2020-10-22T19:06:58.000Z",
      "manageableState": "installed",
      "namespacePrefix": "lightningbuddy",
      "type": "Layout"
    },
    {
      "createdById": "0051U000005tLLaQAM",
      "createdByName": "Toysrus AdminOldUser",
      "createdDate": "2020-10-19T13:25:32.000Z",
      "fileName": "layouts/lightningbuddy__Actions__c-Guideme Actions Layout.layout",
      "fullName": "lightningbuddy__Actions__c-Guideme Actions Layout",
      "id": "00h1U000007QfZdQAK",
      "lastModifiedById": "0051U000005tLLaQAM",
      "lastModifiedByName": "Toysrus AdminOldUser",
      "lastModifiedDate": "2020-10-22T19:06:58.000Z",
      "manageableState": "installed",
      "namespacePrefix": "lightningbuddy",
      "type": "Layout"
    },
    {
      "createdById": "0051U000005tLLaQAM",
      "createdByName": "Toysrus AdminOldUser",
      "createdDate": "2020-10-19T13:25:22.000Z",
      "fileName": "layouts/lightningbuddy__Record_Criteria__c-Record Criteria Layout.layout",
      "fullName": "lightningbuddy__Record_Criteria__c-Record Criteria Layout",
      "id": "00h1U000007QfZYQA0",
      "lastModifiedById": "0051U000005tLLaQAM",
      "lastModifiedByName": "Toysrus AdminOldUser",
      "lastModifiedDate": "2020-10-19T13:25:33.000Z",
      "manageableState": "installed",
      "namespacePrefix": "lightningbuddy",
      "type": "Layout"
    },
    {
      "createdById": "0051U000005tLLaQAM",
      "createdByName": "Toysrus AdminOldUser",
      "createdDate": "2020-08-17T15:09:03.000Z",
      "fileName": "layouts/Knowledge__kav-Lightning Knowledge FAQ Layout.layout",
      "fullName": "Knowledge__kav-Lightning Knowledge FAQ Layout",
      "id": "00h1U000007pXfmQAE",
      "lastModifiedById": "0051U000005tLLaQAM",
      "lastModifiedByName": "Toysrus AdminOldUser",
      "lastModifiedDate": "2020-09-20T17:42:12.000Z",
      "manageableState": "unmanaged",
      "type": "Layout"
    },
    {
      "createdById": "0051U000005XFFIQA4",
      "createdByName": "AstoundOldUser",
      "createdDate": "2019-06-20T14:47:21.000Z",
      "fileName": "layouts/et4ae5__SendDefinition__c-Queued Send Definition Layout.layout",
      "fullName": "et4ae5__SendDefinition__c-Queued Send Definition Layout",
      "id": "00h1U000007TT2ZQAW",
      "lastModifiedById": "0051U000005XFFIQA4",
      "lastModifiedByName": "AstoundOldUser",
      "lastModifiedDate": "2019-06-20T14:49:30.000Z",
      "manageableState": "installed",
      "namespacePrefix": "et4ae5",
      "type": "Layout"
    },
    {
      "createdById": "0051U000001ugPoQAI",
      "createdByName": "salesforce.com, inc.",
      "createdDate": "2022-05-10T14:34:42.000Z",
      "fileName": "layouts/CspTrustedSite-Content Security Policy Trusted Site Layout.layout",
      "fullName": "CspTrustedSite-Content Security Policy Trusted Site Layout",
      "id": "00h8M000000EW2UQAW",
      "lastModifiedById": "0051U000001ugPoQAI",
      "lastModifiedByName": "salesforce.com, inc.",
      "lastModifiedDate": "2022-05-10T14:34:42.000Z",
      "manageableState": "unmanaged",
      "type": "Layout"
    },
    {
      "createdById": "0051U000005tLLaQAM",
      "createdByName": "Toysrus AdminOldUser",
      "createdDate": "2020-08-17T15:06:56.000Z",
      "fileName": "layouts/Knowledge__kav-Knowledge Layout.layout",
      "fullName": "Knowledge__kav-Knowledge Layout",
      "id": "00h1U000007pXfhQAE",
      "lastModifiedById": "0051U000005tLLaQAM",
      "lastModifiedByName": "Toysrus AdminOldUser",
      "lastModifiedDate": "2020-09-22T18:50:47.000Z",
      "manageableState": "unmanaged",
      "type": "Layout"
    },
    {
      "createdById": "0051U000005XFFIQA4",
      "createdByName": "AstoundOldUser",
      "createdDate": "2019-06-20T14:47:21.000Z",
      "fileName": "layouts/et4ae5__SupportRequest__c-Support Request Layout.layout",
      "fullName": "et4ae5__SupportRequest__c-Support Request Layout",
      "id": "00h1U000007TT2bQAG",
      "lastModifiedById": "0051U000005XFFIQA4",
      "lastModifiedByName": "AstoundOldUser",
      "lastModifiedDate": "2019-06-20T14:47:49.000Z",
      "manageableState": "installed",
      "namespacePrefix": "et4ae5",
      "type": "Layout"
    },
    {
      "createdById": "0051U000001L3PBQA0",
      "createdByName": "Craig Turner",
      "createdDate": "2018-12-19T20:27:32.000Z",
      "fileName": "layouts/CaseInteraction-Case Feed Layout.layout",
      "fullName": "CaseInteraction-Case Feed Layout",
      "id": "00h1U000002TMWhQAO",
      "lastModifiedById": "0051U0000060JrUQAU",
      "lastModifiedByName": "Christine Lamonde",
      "lastModifiedDate": "2022-06-06T19:54:08.000Z",
      "manageableState": "unmanaged",
      "type": "Layout"
    },
    {
      "createdById": "0051U000005tLLaQAM",
      "createdByName": "Toysrus AdminOldUser",
      "createdDate": "2020-10-19T13:25:22.000Z",
      "fileName": "layouts/lightningbuddy__Actions__c-File Actions Layout.layout",
      "fullName": "lightningbuddy__Actions__c-File Actions Layout",
      "id": "00h1U000007QfZWQA0",
      "lastModifiedById": "0051U000005tLLaQAM",
      "lastModifiedByName": "Toysrus AdminOldUser",
      "lastModifiedDate": "2020-10-22T19:06:58.000Z",
      "manageableState": "installed",
      "namespacePrefix": "lightningbuddy",
      "type": "Layout"
    },
    {
      "createdById": "0051U000005XFFIQA4",
      "createdByName": "AstoundOldUser",
      "createdDate": "2019-06-20T14:47:48.000Z",
      "fileName": "layouts/et4ae5__SMSDefinition__c-Queued Mobile Send Layout.layout",
      "fullName": "et4ae5__SMSDefinition__c-Queued Mobile Send Layout",
      "id": "00h1U000007TT2gQAG",
      "lastModifiedById": "0051U000005XFFIQA4",
      "lastModifiedByName": "AstoundOldUser",
      "lastModifiedDate": "2019-06-20T14:49:30.000Z",
      "manageableState": "installed",
      "namespacePrefix": "et4ae5",
      "type": "Layout"
    },
    {
      "createdById": "0051U000005XLyGQAW",
      "createdByName": "MCIntegrationOldUser",
      "createdDate": "2020-02-21T20:53:17.000Z",
      "fileName": "layouts/ContactPointEmail-Contact Point Email Layout.layout",
      "fullName": "ContactPointEmail-Contact Point Email Layout",
      "id": "00h1U000007ouNvQAI",
      "lastModifiedById": "0051U000005XLyGQAW",
      "lastModifiedByName": "MCIntegrationOldUser",
      "lastModifiedDate": "2020-02-21T20:53:17.000Z",
      "manageableState": "unmanaged",
      "type": "Layout"
    },
    {
      "createdById": "0051U000001ugPoQAI",
      "createdByName": "salesforce.com, inc.",
      "createdDate": "2022-03-02T21:57:24.000Z",
      "fileName": "layouts/SurveyResponse-Survey Response Layout.layout",
      "fullName": "SurveyResponse-Survey Response Layout",
      "id": "00h1U000007uTwkQAE",
      "lastModifiedById": "0051U000001ugPoQAI",
      "lastModifiedByName": "salesforce.com, inc.",
      "lastModifiedDate": "2022-03-02T21:57:24.000Z",
      "manageableState": "unmanaged",
      "type": "Layout"
    },
    {
      "createdById": "0051U000001L3PBQA0",
      "createdByName": "Craig Turner",
      "createdDate": "2018-12-19T20:27:32.000Z",
      "fileName": "layouts/Global-Global Layout.layout",
      "fullName": "Global-Global Layout",
      "id": "00h1U000002TMWnQAO",
      "lastModifiedById": "0051U000001L3PBQA0",
      "lastModifiedByName": "Craig Turner",
      "lastModifiedDate": "2018-12-19T20:27:32.000Z",
      "manageableState": "unmanaged",
      "type": "Layout"
    },
    {
      "createdById": "0051U000001L3PBQA0",
      "createdByName": "Craig Turner",
      "createdDate": "2018-12-19T20:27:32.000Z",
      "fileName": "layouts/Lead-Lead Layout.layout",
      "fullName": "Lead-Lead Layout",
      "id": "00h1U000002TMWoQAO",
      "lastModifiedById": "0051U000001L3PBQA0",
      "lastModifiedByName": "Craig Turner",
      "lastModifiedDate": "2018-12-19T20:27:32.000Z",
      "manageableState": "unmanaged",
      "type": "Layout"
    },
    {
      "createdById": "0051U000001ugPoQAI",
      "createdByName": "salesforce.com, inc.",
      "createdDate": "2020-07-18T07:07:35.000Z",
      "fileName": "layouts/UserProvAccount-User Provisioning Account Layout.layout",
      "fullName": "UserProvAccount-User Provisioning Account Layout",
      "id": "00h1U000007pJdsQAE",
      "lastModifiedById": "0051U000001ugPoQAI",
      "lastModifiedByName": "salesforce.com, inc.",
      "lastModifiedDate": "2020-07-18T07:07:35.000Z",
      "manageableState": "unmanaged",
      "type": "Layout"
    },
    {
      "createdById": "0051U000001ugPoQAI",
      "createdByName": "salesforce.com, inc.",
      "createdDate": "2021-03-12T19:28:31.000Z",
      "fileName": "layouts/ContactPointTypeConsent-Contact Point Type Consent Layout.layout",
      "fullName": "ContactPointTypeConsent-Contact Point Type Consent Layout",
      "id": "00h1U000007tvF5QAI",
      "lastModifiedById": "0051U000001ugPoQAI",
      "lastModifiedByName": "salesforce.com, inc.",
      "lastModifiedDate": "2021-03-12T19:28:31.000Z",
      "manageableState": "unmanaged",
      "type": "Layout"
    },
    {
      "createdById": "0051U000005XFFIQA4",
      "createdByName": "AstoundOldUser",
      "createdDate": "2019-08-11T20:34:43.000Z",
      "fileName": "layouts/Order-SCC Order Layout.layout",
      "fullName": "Order-SCC Order Layout",
      "id": "00h1U000007FkwEQAS",
      "lastModifiedById": "0051U000005tLLaQAM",
      "lastModifiedByName": "Toysrus AdminOldUser",
      "lastModifiedDate": "2020-12-03T15:07:16.000Z",
      "manageableState": "unmanaged",
      "type": "Layout"
    },
    {
      "createdById": "0051U000001ugPoQAI",
      "createdByName": "salesforce.com, inc.",
      "createdDate": "2022-03-02T19:31:54.000Z",
      "fileName": "layouts/SurveyQuestion-Survey Question Layout.layout",
      "fullName": "SurveyQuestion-Survey Question Layout",
      "id": "00h1U000007uTwGQAU",
      "lastModifiedById": "0051U000001ugPoQAI",
      "lastModifiedByName": "salesforce.com, inc.",
      "lastModifiedDate": "2022-03-02T19:31:54.000Z",
      "manageableState": "unmanaged",
      "type": "Layout"
    },
    {
      "createdById": "0051U000005tLLaQAM",
      "createdByName": "Toysrus AdminOldUser",
      "createdDate": "2020-10-19T13:25:22.000Z",
      "fileName": "layouts/lightningbuddy__Carousel_Image__c-Carousel Image Layout.layout",
      "fullName": "lightningbuddy__Carousel_Image__c-Carousel Image Layout",
      "id": "00h1U000007QfZXQA0",
      "lastModifiedById": "0051U000005tLLaQAM",
      "lastModifiedByName": "Toysrus AdminOldUser",
      "lastModifiedDate": "2020-10-19T13:25:33.000Z",
      "manageableState": "installed",
      "namespacePrefix": "lightningbuddy",
      "type": "Layout"
    },
    {
      "createdById": "0051U000005XFFIQA4",
      "createdByName": "AstoundOldUser",
      "createdDate": "2019-06-20T14:47:49.000Z",
      "fileName": "layouts/et4ae5__SendDefinition__c-Trackable Send Definition Layout 2015-02.layout",
      "fullName": "et4ae5__SendDefinition__c-Trackable Send Definition Layout 2015-02",
      "id": "00h1U000007TT2jQAG",
      "lastModifiedById": "0051U000005XFFIQA4",
      "lastModifiedByName": "AstoundOldUser",
      "lastModifiedDate": "2019-06-20T14:49:30.000Z",
      "manageableState": "installed",
      "namespacePrefix": "et4ae5",
      "type": "Layout"
    },
    {
      "createdById": "0051U000001L3PBQA0",
      "createdByName": "Craig Turner",
      "createdDate": "2018-12-19T20:27:32.000Z",
      "fileName": "layouts/ScorecardMetric-Scorecard Metric Layout.layout",
      "fullName": "ScorecardMetric-Scorecard Metric Layout",
      "id": "00h1U000002TMXUQA4",
      "lastModifiedById": "0051U000001L3PBQA0",
      "lastModifiedByName": "Craig Turner",
      "lastModifiedDate": "2018-12-19T20:27:32.000Z",
      "manageableState": "unmanaged",
      "type": "Layout"
    },
    {
      "createdById": "0051U000001ugPoQAI",
      "createdByName": "salesforce.com, inc.",
      "createdDate": "2018-12-19T20:27:32.000Z",
      "fileName": "layouts/SocialPersona-Social Persona Layout.layout",
      "fullName": "SocialPersona-Social Persona Layout",
      "id": "00h1U000002TMWyQAO",
      "lastModifiedById": "0051U000001ugPoQAI",
      "lastModifiedByName": "salesforce.com, inc.",
      "lastModifiedDate": "2018-12-19T20:27:32.000Z",
      "manageableState": "unmanaged",
      "type": "Layout"
    },
    {
      "createdById": "0051U000005XFFIQA4",
      "createdByName": "AstoundOldUser",
      "createdDate": "2019-06-20T14:47:21.000Z",
      "fileName": "layouts/et4ae5__UEBU__c-User Enabled Business Unit Layout.layout",
      "fullName": "et4ae5__UEBU__c-User Enabled Business Unit Layout",
      "id": "00h1U000007TT2dQAG",
      "lastModifiedById": "0051U000005XFFIQA4",
      "lastModifiedByName": "AstoundOldUser",
      "lastModifiedDate": "2019-06-20T14:47:49.000Z",
      "manageableState": "installed",
      "namespacePrefix": "et4ae5",
      "type": "Layout"
    },
    {
      "createdById": "0051U000001ugPoQAI",
      "createdByName": "salesforce.com, inc.",
      "createdDate": "2018-12-19T20:27:32.000Z",
      "fileName": "layouts/DuplicateRecordSet-Duplicate Record Set Layout.layout",
      "fullName": "DuplicateRecordSet-Duplicate Record Set Layout",
      "id": "00h1U000002TMXFQA4",
      "lastModifiedById": "0051U000001ugPoQAI",
      "lastModifiedByName": "salesforce.com, inc.",
      "lastModifiedDate": "2018-12-19T20:27:32.000Z",
      "manageableState": "unmanaged",
      "type": "Layout"
    },
    {
      "createdById": "0051U000005XFFIQA4",
      "createdByName": "AstoundOldUser",
      "createdDate": "2019-07-31T14:24:36.000Z",
      "fileName": "layouts/Store__c-Store Layout.layout",
      "fullName": "Store__c-Store Layout",
      "id": "00h1U000007FjQqQAK",
      "lastModifiedById": "0051U000005tLLaQAM",
      "lastModifiedByName": "Toysrus AdminOldUser",
      "lastModifiedDate": "2020-09-11T17:11:23.000Z",
      "manageableState": "unmanaged",
      "type": "Layout"
    },
    {
      "createdById": "0051U000001L3PBQA0",
      "createdByName": "Craig Turner",
      "createdDate": "2018-12-19T20:27:32.000Z",
      "fileName": "layouts/ProfileSkillEndorsement-Endorsement Layout.layout",
      "fullName": "ProfileSkillEndorsement-Endorsement Layout",
      "id": "00h1U000002TMXJQA4",
      "lastModifiedById": "0051U000001L3PBQA0",
      "lastModifiedByName": "Craig Turner",
      "lastModifiedDate": "2018-12-19T20:27:32.000Z",
      "manageableState": "unmanaged",
      "type": "Layout"
    },
    {
      "createdById": "0051U000001ugPnQAI",
      "createdByName": "Automated Process",
      "createdDate": "2018-12-19T20:27:32.000Z",
      "fileName": "layouts/PricebookEntry-Price Book Entry Layout.layout",
      "fullName": "PricebookEntry-Price Book Entry Layout",
      "id": "00h1U000002TMXCQA4",
      "lastModifiedById": "0051U000001L3PBQA0",
      "lastModifiedByName": "Craig Turner",
      "lastModifiedDate": "2018-12-19T20:27:32.000Z",
      "manageableState": "unmanaged",
      "type": "Layout"
    },
    {
      "createdById": "0051U000005tLLaQAM",
      "createdByName": "Toysrus AdminOldUser",
      "createdDate": "2020-09-16T05:21:26.000Z",
      "fileName": "layouts/Appeasement__c-Appeasement Layout.layout",
      "fullName": "Appeasement__c-Appeasement Layout",
      "id": "00h1U000007tQUmQAM",
      "lastModifiedById": "0051U000005tLLaQAM",
      "lastModifiedByName": "Toysrus AdminOldUser",
      "lastModifiedDate": "2020-09-16T05:21:39.000Z",
      "manageableState": "unmanaged",
      "type": "Layout"
    },
    {
      "createdById": "0051U000005X8gSQAS",
      "createdByName": "Lou Cicconi",
      "createdDate": "2019-06-15T12:11:09.000Z",
      "fileName": "layouts/Individual-Individual Layout.layout",
      "fullName": "Individual-Individual Layout",
      "id": "00h1U000007TAquQAG",
      "lastModifiedById": "0051U000005X8gSQAS",
      "lastModifiedByName": "Lou Cicconi",
      "lastModifiedDate": "2019-06-15T12:11:09.000Z",
      "manageableState": "unmanaged",
      "type": "Layout"
    },
    {
      "createdById": "0051U000005XFFIQA4",
      "createdByName": "AstoundOldUser",
      "createdDate": "2019-08-01T08:59:20.000Z",
      "fileName": "layouts/Address__c-Address Layout.layout",
      "fullName": "Address__c-Address Layout",
      "id": "00h1U000007FjZOQA0",
      "lastModifiedById": "0051U000005XFFIQA4",
      "lastModifiedByName": "AstoundOldUser",
      "lastModifiedDate": "2019-08-21T15:51:15.000Z",
      "manageableState": "unmanaged",
      "type": "Layout"
    },
    {
      "createdById": "0051U000005X8gSQAS",
      "createdByName": "Lou Cicconi",
      "createdDate": "2019-06-19T18:35:40.000Z",
      "fileName": "layouts/PersonAccount-Person Account Layout.layout",
      "fullName": "PersonAccount-Person Account Layout",
      "id": "00h1U000007TSbPQAW",
      "lastModifiedById": "0051U000008bjiLQAQ",
      "lastModifiedByName": "George Mahesh",
      "lastModifiedDate": "2021-08-03T12:54:05.000Z",
      "manageableState": "unmanaged",
      "type": "Layout"
    },
    {
      "createdById": "0051U000001ugPoQAI",
      "createdByName": "salesforce.com, inc.",
      "createdDate": "2020-10-05T18:30:52.000Z",
      "fileName": "layouts/ServiceResourceSkill-Service Resource Skill Layout.layout",
      "fullName": "ServiceResourceSkill-Service Resource Skill Layout",
      "id": "00h1U000007tTKfQAM",
      "lastModifiedById": "0051U000001ugPoQAI",
      "lastModifiedByName": "salesforce.com, inc.",
      "lastModifiedDate": "2020-10-05T18:30:52.000Z",
      "manageableState": "unmanaged",
      "type": "Layout"
    },
    {
      "createdById": "0051U000005XFFIQA4",
      "createdByName": "AstoundOldUser",
      "createdDate": "2019-07-24T15:44:12.000Z",
      "fileName": "layouts/Child__c-Child Layout.layout",
      "fullName": "Child__c-Child Layout",
      "id": "00h1U000007FiXUQA0",
      "lastModifiedById": "0051U000005tLLaQAM",
      "lastModifiedByName": "Toysrus AdminOldUser",
      "lastModifiedDate": "2021-01-22T12:38:34.000Z",
      "manageableState": "unmanaged",
      "type": "Layout"
    },
    {
      "createdById": "0051U000001ugPoQAI",
      "createdByName": "salesforce.com, inc.",
      "createdDate": "2021-10-09T05:02:35.000Z",
      "fileName": "layouts/BusinessBrand-Business Brand Layout.layout",
      "fullName": "BusinessBrand-Business Brand Layout",
      "id": "00h1U000007ZPvJQAW",
      "lastModifiedById": "0051U000001ugPoQAI",
      "lastModifiedByName": "salesforce.com, inc.",
      "lastModifiedDate": "2021-10-09T05:02:35.000Z",
      "manageableState": "unmanaged",
      "type": "Layout"
    },
    {
      "createdById": "0051U000005XFFIQA4",
      "createdByName": "AstoundOldUser",
      "createdDate": "2019-06-20T14:47:48.000Z",
      "fileName": "layouts/et4ae5__Automated_Send__c-Inactive Send Layout.layout",
      "fullName": "et4ae5__Automated_Send__c-Inactive Send Layout",
      "id": "00h1U000007TT2fQAG",
      "lastModifiedById": "0051U000005XFFIQA4",
      "lastModifiedByName": "AstoundOldUser",
      "lastModifiedDate": "2019-06-20T14:49:29.000Z",
      "manageableState": "installed",
      "namespacePrefix": "et4ae5",
      "type": "Layout"
    },
    {
      "createdById": "0051U000001L3PBQA0",
      "createdByName": "Craig Turner",
      "createdDate": "2018-12-19T20:27:32.000Z",
      "fileName": "layouts/Idea-Idea Layout.layout",
      "fullName": "Idea-Idea Layout",
      "id": "00h1U000002TMX2QAO",
      "lastModifiedById": "0051U000001L3PBQA0",
      "lastModifiedByName": "Craig Turner",
      "lastModifiedDate": "2018-12-19T20:27:32.000Z",
      "manageableState": "unmanaged",
      "type": "Layout"
    },
    {
      "createdById": "0051U000001L3PBQA0",
      "createdByName": "Craig Turner",
      "createdDate": "2018-12-19T20:27:32.000Z",
      "fileName": "layouts/Order-Order Layout.layout",
      "fullName": "Order-Order Layout",
      "id": "00h1U000002TMX4QAO",
      "lastModifiedById": "0051U000005XFFIQA4",
      "lastModifiedByName": "AstoundOldUser",
      "lastModifiedDate": "2019-08-21T13:07:32.000Z",
      "manageableState": "unmanaged",
      "type": "Layout"
    },
    {
      "createdById": "0051U000001L3PBQA0",
      "createdByName": "Craig Turner",
      "createdDate": "2018-12-19T20:27:32.000Z",
      "fileName": "layouts/AccountContactRelation-Account Contact Relationship Layout.layout",
      "fullName": "AccountContactRelation-Account Contact Relationship Layout",
      "id": "00h1U000002TMXXQA4",
      "lastModifiedById": "0051U000001L3PBQA0",
      "lastModifiedByName": "Craig Turner",
      "lastModifiedDate": "2018-12-19T20:27:32.000Z",
      "manageableState": "unmanaged",
      "type": "Layout"
    },
    {
      "createdById": "0051U000001ugPoQAI",
      "createdByName": "salesforce.com, inc.",
      "createdDate": "2021-01-05T18:58:42.000Z",
      "fileName": "layouts/DataUsePurpose-Data Use Purpose Layout.layout",
      "fullName": "DataUsePurpose-Data Use Purpose Layout",
      "id": "00h1U000007q1RVQAY",
      "lastModifiedById": "0051U000001ugPoQAI",
      "lastModifiedByName": "salesforce.com, inc.",
      "lastModifiedDate": "2021-01-05T18:58:42.000Z",
      "manageableState": "unmanaged",
      "type": "Layout"
    },
    {
      "createdById": "0051U000005tLLaQAM",
      "createdByName": "Toysrus AdminOldUser",
      "createdDate": "2020-10-19T13:25:32.000Z",
      "fileName": "layouts/lightningbuddy__Actions__c-Flow Actions Layout.layout",
      "fullName": "lightningbuddy__Actions__c-Flow Actions Layout",
      "id": "00h1U000007QfZcQAK",
      "lastModifiedById": "0051U000005tLLaQAM",
      "lastModifiedByName": "Toysrus AdminOldUser",
      "lastModifiedDate": "2020-10-22T19:06:58.000Z",
      "manageableState": "installed",
      "namespacePrefix": "lightningbuddy",
      "type": "Layout"
    },
    {
      "createdById": "0051U000001L3PBQA0",
      "createdByName": "Craig Turner",
      "createdDate": "2018-12-19T20:27:32.000Z",
      "fileName": "layouts/QuoteLineItem-Quote Line Item Layout.layout",
      "fullName": "QuoteLineItem-Quote Line Item Layout",
      "id": "00h1U000002TMX8QAO",
      "lastModifiedById": "0051U000001L3PBQA0",
      "lastModifiedByName": "Craig Turner",
      "lastModifiedDate": "2018-12-19T20:27:32.000Z",
      "manageableState": "unmanaged",
      "type": "Layout"
    },
    {
      "createdById": "0051U000001L3PBQA0",
      "createdByName": "Craig Turner",
      "createdDate": "2018-12-19T20:27:32.000Z",
      "fileName": "layouts/ProfileSkillUser-Skill User Layout.layout",
      "fullName": "ProfileSkillUser-Skill User Layout",
      "id": "00h1U000002TMXIQA4",
      "lastModifiedById": "0051U000001L3PBQA0",
      "lastModifiedByName": "Craig Turner",
      "lastModifiedDate": "2018-12-19T20:27:32.000Z",
      "manageableState": "unmanaged",
      "type": "Layout"
    },
    {
      "createdById": "0051U000001L3PBQA0",
      "createdByName": "Craig Turner",
      "createdDate": "2018-12-19T20:27:32.000Z",
      "fileName": "layouts/CaseClose-Close Case Layout.layout",
      "fullName": "CaseClose-Close Case Layout",
      "id": "00h1U000002TMX0QAO",
      "lastModifiedById": "0051U0000060JrUQAU",
      "lastModifiedByName": "Christine Lamonde",
      "lastModifiedDate": "2022-06-06T19:54:08.000Z",
      "manageableState": "unmanaged",
      "type": "Layout"
    },
    {
      "createdById": "0051U000001ugPoQAI",
      "createdByName": "salesforce.com, inc.",
      "createdDate": "2018-12-19T20:27:32.000Z",
      "fileName": "layouts/UserAppMenuItem-Application Layout.layout",
      "fullName": "UserAppMenuItem-Application Layout",
      "id": "00h1U000002TMXRQA4",
      "lastModifiedById": "0051U000001ugPoQAI",
      "lastModifiedByName": "salesforce.com, inc.",
      "lastModifiedDate": "2018-12-19T20:27:32.000Z",
      "manageableState": "unmanaged",
      "type": "Layout"
    },
    {
      "createdById": "0051U000005XFFIQA4",
      "createdByName": "AstoundOldUser",
      "createdDate": "2019-06-20T14:47:49.000Z",
      "fileName": "layouts/et4ae5__SendDefinition__c-Send Definition Layout.layout",
      "fullName": "et4ae5__SendDefinition__c-Send Definition Layout",
      "id": "00h1U000007TT2hQAG",
      "lastModifiedById": "0051U000005XFFIQA4",
      "lastModifiedByName": "AstoundOldUser",
      "lastModifiedDate": "2019-06-20T14:49:30.000Z",
      "manageableState": "installed",
      "namespacePrefix": "et4ae5",
      "type": "Layout"
    },
    {
      "createdById": "0051U000001ugPoQAI",
      "createdByName": "salesforce.com, inc.",
      "createdDate": "2021-10-09T05:02:35.000Z",
      "fileName": "layouts/Customer-Customer Layout.layout",
      "fullName": "Customer-Customer Layout",
      "id": "00h1U000007ZPvHQAW",
      "lastModifiedById": "0051U000001ugPoQAI",
      "lastModifiedByName": "salesforce.com, inc.",
      "lastModifiedDate": "2021-10-09T05:02:35.000Z",
      "manageableState": "unmanaged",
      "type": "Layout"
    },
    {
      "createdById": "0051U000005XFFIQA4",
      "createdByName": "AstoundOldUser",
      "createdDate": "2020-07-31T19:39:17.000Z",
      "fileName": "layouts/LiveChatTranscript-Chat Transcript Layout.layout",
      "fullName": "LiveChatTranscript-Chat Transcript Layout",
      "id": "00h1U000007pUGFQA2",
      "lastModifiedById": "0051U000008bjiLQAQ",
      "lastModifiedByName": "George Mahesh",
      "lastModifiedDate": "2021-07-12T14:19:36.000Z",
      "manageableState": "unmanaged",
      "type": "Layout"
    },
    {
      "createdById": "0051U000001L3PBQA0",
      "createdByName": "Craig Turner",
      "createdDate": "2018-12-19T20:27:32.000Z",
      "fileName": "layouts/Asset-Asset Layout.layout",
      "fullName": "Asset-Asset Layout",
      "id": "00h1U000002TMWzQAO",
      "lastModifiedById": "0051U000001L3PBQA0",
      "lastModifiedByName": "Craig Turner",
      "lastModifiedDate": "2018-12-19T20:27:32.000Z",
      "manageableState": "unmanaged",
      "type": "Layout"
    }
  ]
}